{
  "metadata": {
    "approvalListMessageTs": "1754918097.287169",
    "lastUpdated": "2025-08-11T14:13:57.497Z"
  },
  "repositories": {
    "hmcts/ccd-case-ui-toolkit": {
      "pullRequests": {
        "1986": {
          "number": 1986,
          "title": "EXU-3114 tool for pr review process v2",
          "author": "chrisjones-hmcts",
          "url": "https://github.com/hmcts/ccd-case-ui-toolkit/pull/1986",
          "status": "needs_approval",
          "approvals": 0,
          "createdAt": "2025-08-08T14:06:50.278Z",
          "lastUpdated": "2025-08-08T14:06:50.572Z"
        }
      }
    },
    "hmcts/rpx-xui-common-lib": {
      "pullRequests": {
        "509": {
          "number": 509,
          "title": "EXU-3114 tool for pr review process v2",
          "author": "chrisjones-hmcts",
          "url": "https://github.com/hmcts/rpx-xui-common-lib/pull/509",
          "status": "needs_approval",
          "approvals": 0,
          "createdAt": "2025-08-08T14:10:22.754Z",
          "lastUpdated": "2025-08-08T14:10:23.057Z"
        }
      }
    },
    "hmcts/em-media-viewer": {
      "pullRequests": {
        "1195": {
          "changesRequested": true,
          "lastUpdated": "2025-08-11T14:13:57.496Z"
        }
      }
    }
  }
}